Workbook

Sheet Resumen
A1: PILOTO SAT DE INUNDACIONES — ZONAS TURÍSTICAS DE CARTAGENA
A2: Presupuesto del proyecto · Corte a 12.000.000 COP · Bocagrande (zona consolidada) y La Boquilla (zona en potencia)
B4: 1. Descripción del proyecto
B5: Implementación piloto de un Sistema de Alerta Temprana (SAT) de inundaciones orientado a proteger a turistas, residentes y prestadores de servicios en dos puntos de Cartagena: una zona turística consolidada en temporada alta y baja (Bocagrande) y una zona en potencia de desarrollo turístico (La Boquilla). El sistema integra sensores de nivel de agua y pluviómetros IoT, una plataforma de monitoreo y alertas, y protocolos comunitarios de respuesta.
B10: 2. Cifras clave
B11: Indicador | C11: Valor
B12: Presupuesto total del piloto (COP) | C12: =Presupuesto!$E$13 -> $12,000,000
B13: Puntos piloto | C13: 2
B14: Zona 1 — clasificación | C14: Consolidada (alta y baja afluencia)
B15: Zona 2 — clasificación | C15: En potencia de desarrollo turístico
B16: Presupuesto Zona 1 — Bocagrande (COP) | C16: =Presupuesto!$C$13 -> $6,865,000
B17: Presupuesto Zona 2 — La Boquilla (COP) | C17: =Presupuesto!$D$13 -> $5,135,000
B18: Valor turístico estimado protegido — temporada alta (COP) | C18: =Ingresos_Temporada!$G$5+Ingresos_Temporada!$G$7 -> $127,420,312,500
B19: Valor turístico estimado protegido — temporada baja (COP) | C19: =Ingresos_Temporada!$G$6+Ingresos_Temporada!$G$8 -> $154,980,000,000
B21: 3. Contenido del libro
B22: • Supuestos_Turismo — datos y fuentes usados para proyectar visitantes, gasto y temporadas.
B23: • Presupuesto — presupuesto de 12.000.000 COP por categoría y zona, con gráfico de barras.
B24: • Sistema_Contable — clasificación PUC, CAPEX/OPEX y depreciación del presupuesto.
B25: • Distribucion — gráficos de pastel: participación por zona y por categoría de gasto.
B26: • Ingresos_Temporada — estimación del valor turístico por zona y temporada, con gráfico de barras.
B27: • Interpretacion_Datos — cómo las empresas pueden monetizar los datos del SAT.
B28: • Metricas_Ciencia_Datos — KPIs para evaluar el desempeño del modelo de alerta.
B29: • Tabla_Resumen — tabla dinámica (estilo verde oliva y blanco) cruzando categoría, zona y temporada.
B30: • Conclusiones — hallazgos, notas metodológicas y próximos pasos del proyecto.

Sheet Supuestos_Turismo
A1: TURISMO CARTAGENA
A2: Celdas en azul = dato de fuente oficial o estimación propia editable
B4: Variable | C4: Valor | D4: Fuente / observación
B5: Visitantes movilizados, temporada de fin de año 15-dic-2025 a 15-ene-2026 (32 días) | C5: 1300000 | D5: Alcaldía de Cartagena / Corpoturismo, balance temporada dic-2025–ene-2026 (>1,3 millones de visitantes).
B6: Días de la temporada de fin de año usada como referencia | C6: 32 | D6: 15 de diciembre a 15 de enero.
B7: Pasajeros movilizados acumulados a noviembre de 2025 (11 meses, todo el año) | C7: 5500000 | D7: Corpoturismo, balance de gestión 2025 (El Tiempo, dic-2025).
B8: Gasto promedio por turista/día en Cartagena (COP) | C8: 185000 | D8: Revista Semana / Discover — guía de presupuesto de viaje a Cartagena.
B9: Días totales de temporada alta al año (dic-ene + Semana Santa + jun-jul) | C9: 85 | D9: Estimación propia: suma de las tres ventanas de alta afluencia reportadas por Corpoturismo.
B10: Días totales de temporada baja al año | C10: =365-C9 -> 280 | D10: 365 − días de temporada alta (fórmula).
B11: Participación de Zona 1 (Bocagrande) en el flujo turístico total de la ciudad | C11: 0.18 | D11: Estimación propia: zona hotelera consolidada de mayor concentración histórica.
B12: Participación de Zona 2 (La Boquilla) en el flujo turístico total de la ciudad | C12: 0.04 | D12: Estimación propia: zona emergente, oferta hotelera/gastronómica aún limitada.
B13: Gasto promedio turista/día en Zona 2 — La Boquilla (COP) | C13: 90000 | D13: Estimación propia (~49% del gasto de Zona 1) por menor oferta formal de servicios.

Sheet Presupuesto
A1: PRESUPUESTO DEL PROYECTO — 12.000.000 COP
A2: Piloto SAT de inundaciones · Zona 1: Bocagrande (consolidada) · Zona 2: La Boquilla (en potencia)
B4: Categoría de gasto | C4: Zona 1 · Bocagrande (COP) | D4: Zona 2 · La Boquilla (COP) | E4: Total (COP)
B5: Sensores y equipos IoT (nivel de agua, pluviómetros) | C5: 2400000 | D5: 1600000 | E5: =C5+D5 -> $4,000,000
B6: Plataforma de monitoreo, alertas y hosting | C6: 1320000 | D6: 880000 | E6: =C6+D6 -> $2,200,000
B7: Instalación y adecuación de puntos | C7: 650000 | D7: 650000 | E7: =C7+D7 -> $1,300,000
B8: Capacitación comunitaria y a operadores turísticos | C8: 660000 | D8: 540000 | E8: =C8+D8 -> $1,200,000
B9: Señalización y difusión | C9: 495000 | D9: 405000 | E9: =C9+D9 -> $900,000
B10: Mantenimiento y soporte del piloto (3-6 meses) | C10: 840000 | D10: 560000 | E10: =C10+D10 -> $1,400,000
B11: Coordinación y gestión del proyecto | C11: 300000 | D11: 300000 | E11: =C11+D11 -> $600,000
B12: Imprevistos (contingencia) | C12: 200000 | D12: 200000 | E12: =C12+D12 -> $400,000
B13: TOTAL | C13: =SUM(C5:C12) -> $6,865,000 | D13: =SUM(D5:D12) -> $5,135,000 | E13: =SUM(E5:E12) -> $12,000,000

Sheet Sistema_Contable
A1: SISTEMA CONTABLE DEL PROYECTO
A2: Clasificación bajo el Plan Único de Cuentas (PUC – Colombia) · CAPEX / OPEX · depreciación en línea recta
B4: 4. Clasificación contable por categoría
B5: Cuenta PUC | C5: Categoría | D5: Tipo | E5: Monto (COP) | F5: Naturaleza | G5: Vida útil (meses) | H5: Depreciación/ amortización mensual (COP)
B6: 1528 - Equipo de comunicación y computación | C6: Sensores y equipos IoT (nivel de agua, pluviómetros) | D6: Activo (CAPEX) | E6: =Presupuesto!E5 -> $4,000,000 | F6: Débito | G6: 36 | H6: =E6/G6 -> $111,111
B7: 1635 - Software (activo intangible) | C7: Plataforma de monitoreo, alertas y hosting | D7: Activo (CAPEX) | E7: =Presupuesto!E6 -> $2,200,000 | F7: Débito | G7: 24 | H7: =E7/G7 -> $91,667
B8: 1524 - Equipo de oficina / adecuaciones | C8: Instalación y adecuación de puntos | D8: Activo (CAPEX) | E8: =Presupuesto!E7 -> $1,300,000 | F8: Débito | G8: 60 | H8: =E8/G8 -> $21,667
B9: 511010 - Gastos de capacitación | C9: Capacitación comunitaria y a operadores turísticos | D9: Gasto (OPEX) | E9: =Presupuesto!E8 -> $1,200,000 | F9: Débito (gasto) | G9: — | H9: No aplica (gasto del periodo)
B10: 523525 - Publicidad y propaganda | C10: Señalización y difusión | D10: Gasto (OPEX) | E10: =Presupuesto!E9 -> $900,000 | F10: Débito (gasto) | G10: — | H10: No aplica (gasto del periodo)
B11: 512020 - Mantenimiento de equipo | C11: Mantenimiento y soporte del piloto (3-6 meses) | D11: Gasto (OPEX) | E11: =Presupuesto!E10 -> $1,400,000 | F11: Débito (gasto) | G11: — | H11: No aplica (gasto del periodo)
B12: 510506 - Honorarios / gestión de proyectos | C12: Coordinación y gestión del proyecto | D12: Gasto (OPEX) | E12: =Presupuesto!E11 -> $600,000 | F12: Débito (gasto) | G12: — | H12: No aplica (gasto del periodo)
B13: 529530 - Gastos diversos / imprevistos | C13: Imprevistos (contingencia) | D13: Gasto (OPEX) | E13: =Presupuesto!E12 -> $400,000 | F13: Débito (gasto) | G13: — | H13: No aplica (gasto del periodo)
B14: TOTAL | E14: =SUM(E6:E13) -> $12,000,000
B16: 5. Resumen CAPEX vs. OPEX
B17: Componente | C17: Monto (COP) | E17: Participación
B18: CAPEX — Activos (equipos, software, obra) | C18: =SUMIF(D6:D13,"Activo (CAPEX)",E6:E13) -> $7,500,000 | E18: =C18/E14 -> 62.5%
B19: OPEX — Gastos operativos y de gestión | C19: =SUMIF(D6:D13,"Gasto (OPEX)",E6:E13) -> $4,500,000 | E19: =C19/E14 -> 37.5%
B21: 6. Depreciación y amortización mensual total
B22: Cargo mensual estimado a resultados (COP/mes) | E22: =SUMIF(D6:D13,"Activo (CAPEX)",H6:H13) -> $224,444

Sheet Distribucion
A1: DISTRIBUCIÓN DEL PRESUPUESTO
A2: Participación por zona y por categoría de gasto
B4: Zona | C4: Presupuesto (COP) | E4: Categoría | F4: Presupuesto total (COP)
B5: Zona 1 · Bocagrande | C5: =Presupuesto!C13 -> $6,865,000 | E5: Sensores y equipos IoT (nivel de agua, pluviómetros) | F5: =Presupuesto!E5 -> $4,000,000
B6: Zona 2 · La Boquilla | C6: =Presupuesto!D13 -> $5,135,000 | E6: Plataforma de monitoreo, alertas y hosting | F6: =Presupuesto!E6 -> $2,200,000
E7: Instalación y adecuación de puntos | F7: =Presupuesto!E7 -> $1,300,000
E8: Capacitación comunitaria y a operadores turísticos | F8: =Presupuesto!E8 -> $1,200,000
E9: Señalización y difusión | F9: =Presupuesto!E9 -> $900,000
E10: Mantenimiento y soporte del piloto (3-6 meses) | F10: =Presupuesto!E10 -> $1,400,000
E11: Coordinación y gestión del proyecto | F11: =Presupuesto!E11 -> $600,000
E12: Imprevistos (contingencia) | F12: =Presupuesto!E12 -> $400,000

Sheet Ingresos_Temporada
A1: VALOR TURÍSTICO ESTIMADO POR ZONA Y TEMPORADA
A2: Estimación de la actividad económica turística que el SAT contribuye a proteger (no es ingreso del proyecto)
B4: Zona | C4: Temporada | D4: Visitantes/día (estimado) | E4: Gasto/día (COP) | F4: Días de temporada | G4: Valor turístico estimado (COP)
B5: Zona 1 · Bocagrande | C5: Alta | D5: =Supuestos_Turismo!$C$5/Supuestos_Turismo!$C$6*Supuestos_Turismo!$C$11 -> 7,313 | E5: =Supuestos_Turismo!$C$8 -> $185,000 | F5: =Supuestos_Turismo!$C$9 -> 85 | G5: =D5*E5*F5 -> $114,989,062,500
B6: Zona 1 · Bocagrande | C6: Baja | D6: =(Supuestos_Turismo!$C$7-Supuestos_Turismo!$C$5)/Supuestos_Turismo!$C$10*Supuestos_Turismo!$C$11 -> 2,700 | E6: =Supuestos_Turismo!$C$8 -> $185,000 | F6: =Supuestos_Turismo!$C$10 -> 280 | G6: =D6*E6*F6 -> $139,860,000,000
B7: Zona 2 · La Boquilla | C7: Alta | D7: =Supuestos_Turismo!$C$5/Supuestos_Turismo!$C$6*Supuestos_Turismo!$C$12 -> 1,625 | E7: =Supuestos_Turismo!$C$13 -> $90,000 | F7: =Supuestos_Turismo!$C$9 -> 85 | G7: =D7*E7*F7 -> $12,431,250,000
B8: Zona 2 · La Boquilla | C8: Baja | D8: =(Supuestos_Turismo!$C$7-Supuestos_Turismo!$C$5)/Supuestos_Turismo!$C$10*Supuestos_Turismo!$C$12 -> 600 | E8: =Supuestos_Turismo!$C$13 -> $90,000 | F8: =Supuestos_Turismo!$C$10 -> 280 | G8: =D8*E8*F8 -> $15,120,000,000
B10: TOTAL | G10: =SUM(G5:G8) -> $282,400,312,500

Sheet Interpretacion_Datos
A1: OPORTUNIDADES DE NEGOCIO
A2: Cómo los datos del SAT pueden generar ingresos para empresas turísticas y aseguradoras
B4: 7. Qué mide el SAT y cómo se interpreta
B5: El SAT captura tres tipos de datos: nivel de agua e intensidad de lluvia (sensores IoT y pluviómetros), variables de contexto (marea, temporada) y flujo de visitantes por zona. La interpretación consiste en cruzar estas series con umbrales de riesgo para generar tres niveles de alerta (verde, amarillo, rojo) y, más importante, en traducir ese nivel en una acción concreta — evacuación, cierre temporal de playas, activación de protocolos — en vez de limitarse a reportar un dato aislado.
B10: 8. Cómo las empresas pueden ganar dinero con esta solución
B11: Mecanismo | C11: Cómo funciona y a quién beneficia
B12: Seguros paramétricos | C12: Aseguradoras pueden ofrecer pólizas para hoteles y operadores turísticos que pagan automáticamente cuando el sensor supera un umbral de nivel de agua o lluvia, sin necesidad de peritaje. El sector turístico ya usa este modelo frente a huracanes y clima adverso porque cubre la pérdida de ingresos por cancelaciones, no solo el daño físico, y agiliza el pago frente al seguro tradicional.
B13: Dato como servicio (Data as a Service) | C13: El operador del SAT puede vender acceso al dashboard y a las alertas en tiempo real a hoteles, agencias de tours, restaurantes y aseguradoras mediante una suscripción mensual, evitando que cada empresa deba instalar sus propios sensores.
B14: Tarificación dinámica | C14: Hoteles y operadores de playa pueden ajustar precios y disponibilidad de reservas según el nivel de riesgo previsto para los próximos días, protegiendo margen en temporada alta y evitando sobreventa en días de alerta.
B15: Continuidad operativa y reputación | C15: Un sello de 'zona con SAT activo' es un argumento de marketing y de gestión de riesgo frente a agencias de viaje y aseguradoras, y reduce el tiempo de cierre tras un evento al activar protocolos antes de que ocurra la inundación.
B16: Mantenimiento predictivo de infraestructura | C16: Cadenas hoteleras e infraestructura pública (malecón, vías) pueden usar el histórico de niveles de agua para priorizar mantenimiento preventivo en los puntos más expuestos, reduciendo costos de reparación de emergencia.

Sheet Metricas_Ciencia_Datos
A1: MÉTRICAS
A2: Indicadores para evaluar el desempeño del modelo de alerta y la calidad de los datos
B4: 9. Métricas de desempeño del modelo de alerta
B5: Métrica | C5: Qué mide | D5: Meta sugerida
B6: Precisión (Precision) | C6: De las alertas emitidas, qué porcentaje correspondió a un evento real de inundación (evita falsas alarmas que erosionan la confianza). | D6: ≥ 85%
B7: Sensibilidad (Recall) | C7: De los eventos reales de inundación, qué porcentaje fue detectado a tiempo por el sistema. | D7: ≥ 90%
B8: F1-score | C8: Balance entre precisión y sensibilidad; útil cuando el costo de una falsa alarma y el de una alerta perdida son ambos altos. | D8: ≥ 0,85
B9: Tiempo de anticipación (lead time) | C9: Minutos u horas entre la emisión de la alerta y el momento en que el nivel de agua alcanza el umbral crítico. | D9: ≥ 30 min
B10: Tasa de falsos positivos | C10: Proporción de alertas emitidas que no correspondieron a un evento real; impacta directamente la credibilidad ante hoteles y turistas. | D10: ≤ 10%
B11: RMSE / MAE en la predicción de nivel de agua | C11: Error promedio entre el nivel de agua pronosticado y el observado, en centímetros. | D11: Definir línea base tras 3 meses de datos
B12: Completitud de datos (uptime de sensores) | C12: Porcentaje de tiempo en que cada sensor reporta datos válidos, clave para no perder eventos por fallas de hardware o conectividad. | D12: ≥ 95%
B13: Latencia del dato | C13: Tiempo entre la medición en campo y su disponibilidad en el panel de monitoreo. | D13: ≤ 2 min
B15: 10. Cadencia de monitoreo de las métricas
B16: Nivel operativo (uptime, latencia) | C16: Revisión diaria automática desde la plataforma de monitoreo.
B17: Nivel de modelo (precisión, recall, RMSE) | C17: Revisión mensual, comparando alertas emitidas contra eventos reales registrados por el equipo en campo.

Sheet Tabla_Resumen
A1: TABLA DINÁMICA — PRESUPUESTO POR CATEGORÍA Y ZONA
A2: Estilo verde oliva y blanco · valores calculados con SUMIFS sobre Datos_Base
B4: Categoría | C4: Zona 1 · Bocagrande | D4: Zona 2 · La Boquilla | E4: Total general
B5: Sensores y equipos IoT (nivel de agua, pluviómetros) | C5: =SUMIFS(Datos_Base!$D$5:$D$20,Datos_Base!$B$5:$B$20,$B5,Datos_Base!$C$5:$C$20,C$4) -> $2,400,000 | D5: =SUMIFS(Datos_Base!$D$5:$D$20,Datos_Base!$B$5:$B$20,$B5,Datos_Base!$C$5:$C$20,D$4) -> $1,600,000 | E5: =C5+D5 -> $4,000,000
B6: Plataforma de monitoreo, alertas y hosting | C6: =SUMIFS(Datos_Base!$D$5:$D$20,Datos_Base!$B$5:$B$20,$B6,Datos_Base!$C$5:$C$20,C$4) -> $1,320,000 | D6: =SUMIFS(Datos_Base!$D$5:$D$20,Datos_Base!$B$5:$B$20,$B6,Datos_Base!$C$5:$C$20,D$4) -> $880,000 | E6: =C6+D6 -> $2,200,000
B7: Instalación y adecuación de puntos | C7: =SUMIFS(Datos_Base!$D$5:$D$20,Datos_Base!$B$5:$B$20,$B7,Datos_Base!$C$5:$C$20,C$4) -> $650,000 | D7: =SUMIFS(Datos_Base!$D$5:$D$20,Datos_Base!$B$5:$B$20,$B7,Datos_Base!$C$5:$C$20,D$4) -> $650,000 | E7: =C7+D7 -> $1,300,000
B8: Capacitación comunitaria y a operadores turísticos | C8: =SUMIFS(Datos_Base!$D$5:$D$20,Datos_Base!$B$5:$B$20,$B8,Datos_Base!$C$5:$C$20,C$4) -> $660,000 | D8: =SUMIFS(Datos_Base!$D$5:$D$20,Datos_Base!$B$5:$B$20,$B8,Datos_Base!$C$5:$C$20,D$4) -> $540,000 | E8: =C8+D8 -> $1,200,000
B9: Señalización y difusión | C9: =SUMIFS(Datos_Base!$D$5:$D$20,Datos_Base!$B$5:$B$20,$B9,Datos_Base!$C$5:$C$20,C$4) -> $495,000 | D9: =SUMIFS(Datos_Base!$D$5:$D$20,Datos_Base!$B$5:$B$20,$B9,Datos_Base!$C$5:$C$20,D$4) -> $405,000 | E9: =C9+D9 -> $900,000
B10: Mantenimiento y soporte del piloto (3-6 meses) | C10: =SUMIFS(Datos_Base!$D$5:$D$20,Datos_Base!$B$5:$B$20,$B10,Datos_Base!$C$5:$C$20,C$4) -> $840,000 | D10: =SUMIFS(Datos_Base!$D$5:$D$20,Datos_Base!$B$5:$B$20,$B10,Datos_Base!$C$5:$C$20,D$4) -> $560,000 | E10: =C10+D10 -> $1,400,000
B11: Coordinación y gestión del proyecto | C11: =SUMIFS(Datos_Base!$D$5:$D$20,Datos_Base!$B$5:$B$20,$B11,Datos_Base!$C$5:$C$20,C$4) -> $300,000 | D11: =SUMIFS(Datos_Base!$D$5:$D$20,Datos_Base!$B$5:$B$20,$B11,Datos_Base!$C$5:$C$20,D$4) -> $300,000 | E11: =C11+D11 -> $600,000
B12: Imprevistos (contingencia) | C12: =SUMIFS(Datos_Base!$D$5:$D$20,Datos_Base!$B$5:$B$20,$B12,Datos_Base!$C$5:$C$20,C$4) -> $200,000 | D12: =SUMIFS(Datos_Base!$D$5:$D$20,Datos_Base!$B$5:$B$20,$B12,Datos_Base!$C$5:$C$20,D$4) -> $200,000 | E12: =C12+D12 -> $400,000
B13: Total general | C13: =SUM(C5:C12) -> $6,865,000 | D13: =SUM(D5:D12) -> $5,135,000 | E13: =SUM(E5:E12) -> $12,000,000
B16: TABLA DINÁMICA — VALOR TURÍSTICO POR ZONA Y TEMPORADA
B17: Zona | C17: Temporada alta (COP) | D17: Temporada baja (COP) | E17: Total zona (COP)
B18: Zona 1 · Bocagrande | C18: =SUMIFS(Ingresos_Temporada!$G$5:$G$8,Ingresos_Temporada!$B$5:$B$8,$B18,Ingresos_Temporada!$C$5:$C$8,"Alta") -> $114,989,062,500 | D18: =SUMIFS(Ingresos_Temporada!$G$5:$G$8,Ingresos_Temporada!$B$5:$B$8,$B18,Ingresos_Temporada!$C$5:$C$8,"Baja") -> $139,860,000,000 | E18: =C18+D18 -> $254,849,062,500
B19: Zona 2 · La Boquilla | C19: =SUMIFS(Ingresos_Temporada!$G$5:$G$8,Ingresos_Temporada!$B$5:$B$8,$B19,Ingresos_Temporada!$C$5:$C$8,"Alta") -> $12,431,250,000 | D19: =SUMIFS(Ingresos_Temporada!$G$5:$G$8,Ingresos_Temporada!$B$5:$B$8,$B19,Ingresos_Temporada!$C$5:$C$8,"Baja") -> $15,120,000,000 | E19: =C19+D19 -> $27,551,250,000
B20: Total general | C20: =SUM(C18:C19) -> $127,420,312,500 | D20: =SUM(D18:D19) -> $154,980,000,000 | E20: =SUM(E18:E19) -> $282,400,312,500

Sheet Conclusiones
A1: CONCLUSIONES
A2: Piloto SAT de inundaciones en zonas turísticas de Cartagena
B4: 11. Conclusiones del proyecto
B5: Viabilidad presupuestal
B6: El piloto es viable con 12.000.000 COP siempre que se mantenga el alcance de dos puntos (Bocagrande y La Boquilla) y un horizonte de 3 a 6 meses; ampliar a más zonas o a un monitoreo permanente requiere un presupuesto adicional, principalmente en mantenimiento y coordinación.
B10: Metodología de cifras turísticas
B11: Las cifras de afluencia y gasto turístico se basan en reportes oficiales de la Alcaldía de Cartagena y Corpoturismo (ver hoja Supuestos_Turismo). La participación de cada zona en el flujo turístico total y el gasto diferencial de la zona en potencia son estimaciones propias y deben validarse con datos primarios de cada zona antes de presentar el documento a un tercero.
B15: Uso de las celdas editables
B16: Las celdas en azul (Supuestos_Turismo y Presupuesto) son entradas editables. El presupuesto total debe permanecer en 12.000.000 COP; si se redistribuyen montos entre categorías o zonas, los totales y las hojas dependientes (Distribucion, Ingresos_Temporada, Sistema_Contable, Tabla_Resumen) se recalculan automáticamente.
B20: Alcance de las tablas dinámicas
B21: Las tablas de la hoja Tabla_Resumen funcionan como tablas dinámicas: agregan automáticamente los datos de Datos_Base e Ingresos_Temporada mediante fórmulas SUMIFS. Para una tabla dinámica nativa de Excel, seleccione los datos de origen y use Insertar > Tabla dinámica; el estilo verde oliva y blanco puede aplicarse desde Diseño > Estilos de tabla dinámica > Nuevo estilo de tabla dinámica.
B25: Alcance del valor turístico estimado
B26: El valor turístico estimado por zona y temporada (hoja Ingresos_Temporada) representa la actividad económica turística de cada zona, no una ganancia generada por el SAT. Se usa como referencia del valor económico que el sistema ayuda a proteger frente a interrupciones por inundación, y para dimensionar el presupuesto del piloto frente al tamaño de la economía turística local.
B30: Modelo de sostenibilidad financiera
... B36: Validar los supuestos de participación turística por zona con Corpoturismo o los gremios hoteleros locales, definir la línea base de las métricas de ciencia de datos (hoja Metricas_Ciencia_Datos) durante los primeros tres meses de operación, y explorar acuerdos comerciales con al menos una aseguradora para el piloto de seguro paramétrico.

Sheet Datos_Base
A1: DATOS BASE — PRESUPUESTO
B4: Categoría | C4: Zona | D4: Monto (COP)
B5: Sensores y equipos IoT (nivel de agua, pluviómetros) | C5: Zona 1 · Bocagrande | D5: =Presupuesto!C5 -> $2,400,000
B6: Sensores y equipos IoT (nivel de agua, pluviómetros) | C6: Zona 2 · La Boquilla | D6: =Presupuesto!D5 -> $1,600,000
B7: Plataforma de monitoreo, alertas y hosting | C7: Zona 1 · Bocagrande | D7: =Presupuesto!C6 -> $1,320,000
B8: Plataforma de monitoreo, alertas y hosting | C8: Zona 2 · La Boquilla | D8: =Presupuesto!D6 -> $880,000
B9: Instalación y adecuación de puntos | C9: Zona 1 · Bocagrande | D9: =Presupuesto!C7 -> $650,000
B10: Instalación y adecuación de puntos | C10: Zona 2 · La Boquilla | D10: =Presupuesto!D7 -> $650,000
B11: Capacitación comunitaria y a operadores turísticos | C11: Zona 1 · Bocagrande | D11: =Presupuesto!C8 -> $660,000
B12: Capacitación comunitaria y a operadores turísticos | C12: Zona 2 · La Boquilla | D12: =Presupuesto!D8 -> $540,000
B13: Señalización y difusión | C13: Zona 1 · Bocagrande | D13: =Presupuesto!C9 -> $495,000
B14: Señalización y difusión | C14: Zona 2 · La Boquilla | D14: =Presupuesto!D9 -> $405,000
B15: Mantenimiento y soporte del piloto (3-6 meses) | C15: Zona 1 · Bocagrande | D15: =Presupuesto!C10 -> $840,000
B16: Mantenimiento y soporte del piloto (3-6 meses) | C16: Zona 2 · La Boquilla | D16: =Presupuesto!D10 -> $560,000
B17: Coordinación y gestión del proyecto | C17: Zona 1 · Bocagrande | D17: =Presupuesto!C11 -> $300,000
B18: Coordinación y gestión del proyecto | C18: Zona 2 · La Boquilla | D18: =Presupuesto!D11 -> $300,000
B19: Imprevistos (contingencia) | C19: Zona 1 · Bocagrande | D19: =Presupuesto!C12 -> $200,000
B20: Imprevistos (contingencia) | C20: Zona 2 · La Boquilla | D20: =Presupuesto!D12 -> $200,000
